igdiscover/Snakefile
igdiscover/__init__.py
igdiscover/__main__.py
igdiscover/_version.py
igdiscover/align.py
igdiscover/cluster.py
igdiscover/config.py
igdiscover/dna.py
igdiscover/empty.aux
igdiscover/igblast.py
igdiscover/igdiscover.yaml
igdiscover/readlenhistogram.py
igdiscover/species.py
igdiscover/table.py
igdiscover/trie.py
igdiscover/utils.py
igdiscover/cli/__init__.py
igdiscover/cli/augment.py
igdiscover/cli/clonoquery.py
igdiscover/cli/clonotypes.py
igdiscover/cli/clusterplot.py
igdiscover/cli/commonv.py
igdiscover/cli/config.py
igdiscover/cli/count.py
igdiscover/cli/dbdiff.py
igdiscover/cli/dendrogram.py
igdiscover/cli/dereplicate.py
igdiscover/cli/discover.py
igdiscover/cli/discoverjd.py
igdiscover/cli/errorplot.py
igdiscover/cli/filter.py
igdiscover/cli/germlinefilter.py
igdiscover/cli/group.py
igdiscover/cli/haplotype.py
igdiscover/cli/igblastwrap.py
igdiscover/cli/init.py
igdiscover/cli/merge.py
igdiscover/cli/multidiscover.py
igdiscover/cli/plotalleles.py
igdiscover/cli/rename.py
igdiscover/cli/run.py
igdiscover/cli/union.py
igdiscover/cli/upstream.py
igdiscover-0.15.1.dist-info/LICENSE
igdiscover-0.15.1.dist-info/METADATA
igdiscover-0.15.1.dist-info/WHEEL
igdiscover-0.15.1.dist-info/entry_points.txt
igdiscover-0.15.1.dist-info/top_level.txt
igdiscover-0.15.1.dist-info/RECORD
