Metadata-Version: 2.1
Name: igdiscover
Version: 0.15.1
Summary: Analyze antibody repertoires and discover new V genes
Home-page: https://igdiscover.se/
Author: Marcel Martin
Author-email: marcel.martin@scilifelab.se
License: MIT
Project-URL: Changelog, http://docs.igdiscover.se/en/stable/changes.html
Platform: UNKNOWN
Classifier: Development Status :: 4 - Beta
Classifier: Environment :: Console
Classifier: Intended Audience :: Science/Research
Classifier: License :: OSI Approved :: MIT License
Classifier: Natural Language :: English
Classifier: Programming Language :: Python :: 3
Classifier: Topic :: Scientific/Engineering :: Bio-Informatics
Requires-Python: >=3.6
License-File: LICENSE
